clipboard_sync_client.py
clipboard_sync_client-0.0.29.dist-info/LICENSE
clipboard_sync_client-0.0.29.dist-info/METADATA
clipboard_sync_client-0.0.29.dist-info/WHEEL
clipboard_sync_client-0.0.29.dist-info/entry_points.txt
clipboard_sync_client-0.0.29.dist-info/top_level.txt
clipboard_sync_client-0.0.29.dist-info/RECORD
