Metadata-Version: 2.1
Name: clipboard-sync-client
Version: 0.0.29
Summary: client for sync clipboard between different computers
Home-page: https://github.com/zkytech/cross_platform_clipboard_sync
Author: zkytech
Author-email: zhangkunyuan@hotmail.com
License: MIT
Platform: UNKNOWN
Classifier: Development Status :: 4 - Beta
Classifier: License :: OSI Approved :: MIT License
Classifier: Environment :: Console
Classifier: Intended Audience :: End Users/Desktop
Classifier: Natural Language :: English
Classifier: Operating System :: POSIX :: Linux
Classifier: Operating System :: MacOS :: MacOS X
Classifier: Operating System :: POSIX :: SunOS/Solaris
Classifier: Programming Language :: Python :: 3.6
Classifier: Programming Language :: Python :: 3.7
Classifier: Programming Language :: Python :: 3.8
Classifier: Programming Language :: Python :: 3.9
Classifier: Programming Language :: Python :: 3.10
Classifier: Topic :: Utilities
Classifier: Topic :: System
Requires-Python: ~=3.6
License-File: LICENSE
Requires-Dist: pyperclip (==1.8.2)
Requires-Dist: python-socketio (==5.4.1)
Requires-Dist: requests (==2.26.0)
Requires-Dist: urllib3 (==1.26.7)
Requires-Dist: websocket-client (==1.2.1)
